README.md
setup.py
north_devices/__init__.py
north_devices/__version__.py
north_devices.egg-info/PKG-INFO
north_devices.egg-info/SOURCES.txt
north_devices.egg-info/dependency_links.txt
north_devices.egg-info/requires.txt
north_devices.egg-info/top_level.txt
north_devices/potentiostat/__init__.py
north_devices/potentiostat/bio_logic.py
north_devices/power_supplies/__init__.py
north_devices/power_supplies/keithley.py
north_devices/pumps/__init__.py
north_devices/pumps/tecan_cavro.py
north_devices/scales/__init__.py
north_devices/scales/scientech_zeta.py