Metadata-Version: 2.1
Name: north-devices
Version: 0.3.5
Summary: Drivers and utilities for third-party North Robotics devices
Home-page: https://gitlab.com/north-robotics/north_devices
Author: Sean Clark
Author-email: sclark@northrobotics.com
License: MIT
Platform: UNKNOWN
Requires-Python: >=3.6.0
